{
    "errno": 0,
    "errmsg": "ok",
    "requestId": "0a93c06c6996699727ba33205445a802",
    "time": 1771465111,
    "msectime": 1771465111983,
    "data": {
        "orderList": [
            {
                "orderId": "5764660008298021113",
                "orderIndex": 278011,
                "displayNum": "#278011",
                "sourceDescription": "",
                "shopId": "5764607714484028278",
                "displayStatus": 4,
                "initiator": "",
                "responsible": "",
                "reason": "",
                "deliveryType": 1,
                "deliveryTypeText": "DiDi",
                "currency": "COP",
                "orderIncome": 1988300,
                "orderIncomeDisplay": "$19.883",
                "incomeReduce": 0,
                "incomeReduceDisplay": "",
                "createTime": 1771462130,
                "createTimeOffsetInfo": {
                    "timestamp": 1771462130,
                    "offset": -18000
                },
                "displayInfo": {
                    "tips": "",
                    "statusText": "Completado",
                    "countDown": false,
                    "tags": [],
                    "type": 0
                },
                "shopPaidStatus": 0,
                "receiverInfo": {
                    "name": "Andres"
                },
                "statusTag": [],
                "subtotal": 4240000,
                "subtotalDisplay": "$42.400",
                "payType": 1,
                "payTag": {
                    "payType": 1
                }
            },
            {
                "orderId": "5764660012991447251",
                "orderIndex": 278010,
                "displayNum": "#278010",
                "sourceDescription": "",
                "shopId": "5764607714484028278",
                "displayStatus": 4,
                "initiator": "",
                "responsible": "",
                "reason": "",
                "deliveryType": 1,
                "deliveryTypeText": "DiDi",
                "currency": "COP",
                "orderIncome": 2644000,
                "orderIncomeDisplay": "$26.440",
                "incomeReduce": 0,
                "incomeReduceDisplay": "",
                "createTime": 1771461481,
                "createTimeOffsetInfo": {
                    "timestamp": 1771461481,
                    "offset": -18000
                },
                "displayInfo": {
                    "tips": "",
                    "statusText": "Completado",
                    "countDown": false,
                    "tags": [],
                    "type": 0
                },
                "shopPaidStatus": 0,
                "receiverInfo": {
                    "name": "Jesus ricardo"
                },
                "statusTag": [],
                "subtotal": 5030000,
                "subtotalDisplay": "$50.300",
                "payType": 1,
                "payTag": {
                    "payType": 1
                }
            },
            {
                "orderId": "5764659861874868429",
                "orderIndex": 278009,
                "displayNum": "#278009",
                "sourceDescription": "",
                "shopId": "5764607714484028278",
                "displayStatus": 4,
                "initiator": "",
                "responsible": "",
                "reason": "",
                "deliveryType": 1,
                "deliveryTypeText": "DiDi",
                "currency": "COP",
                "orderIncome": 4467000,
                "orderIncomeDisplay": "$44.670",
                "incomeReduce": 0,
                "incomeReduceDisplay": "",
                "createTime": 1771460993,
                "createTimeOffsetInfo": {
                    "timestamp": 1771460993,
                    "offset": -18000
                },
                "displayInfo": {
                    "tips": "",
                    "statusText": "Completado",
                    "countDown": false,
                    "tags": [],
                    "type": 0
                },
                "shopPaidStatus": 0,
                "receiverInfo": {
                    "name": "Mariana"
                },
                "statusTag": [],
                "subtotal": 8280000,
                "subtotalDisplay": "$82.800",
                "payType": 1,
                "payTag": {
                    "payType": 1
                }
            },
            {
                "orderId": "5764659904468025550",
                "orderIndex": 278008,
                "displayNum": "#278008",
                "sourceDescription": "",
                "shopId": "5764607714484028278",
                "displayStatus": 4,
                "initiator": "",
                "responsible": "",
                "reason": "",
                "deliveryType": 1,
                "deliveryTypeText": "DiDi",
                "currency": "COP",
                "orderIncome": 4992600,
                "orderIncomeDisplay": "$49.926",
                "incomeReduce": 0,
                "incomeReduceDisplay": "",
                "createTime": 1771460262,
                "createTimeOffsetInfo": {
                    "timestamp": 1771460262,
                    "offset": -18000
                },
                "displayInfo": {
                    "tips": "",
                    "statusText": "Completado",
                    "countDown": false,
                    "tags": [],
                    "type": 0
                },
                "shopPaidStatus": 0,
                "receiverInfo": {
                    "name": "Carolayn"
                },
                "statusTag": [],
                "subtotal": 9840000,
                "subtotalDisplay": "$98.400",
                "payType": 1,
                "payTag": {
                    "payType": 1
                }
            },
            {
                "orderId": "5764659867830780097",
                "orderIndex": 278007,
                "displayNum": "#278007",
                "sourceDescription": "",
                "shopId": "5764607714484028278",
                "displayStatus": 4,
                "initiator": "",
                "responsible": "",
                "reason": "",
                "deliveryType": 1,
                "deliveryTypeText": "DiDi",
                "currency": "COP",
                "orderIncome": 3406300,
                "orderIncomeDisplay": "$34.063",
                "incomeReduce": 0,
                "incomeReduceDisplay": "",
                "createTime": 1771460183,
                "createTimeOffsetInfo": {
                    "timestamp": 1771460183,
                    "offset": -18000
                },
                "displayInfo": {
                    "tips": "",
                    "statusText": "Completado",
                    "countDown": false,
                    "tags": [],
                    "type": 0
                },
                "shopPaidStatus": 21,
                "receiverInfo": {
                    "name": "Ander"
                },
                "statusTag": [],
                "subtotal": 6840000,
                "subtotalDisplay": "$68.400",
                "payType": 1,
                "payTag": {
                    "payType": 1
                }
            },
            {
                "orderId": "5764659832040784070",
                "orderIndex": 278006,
                "displayNum": "#278006",
                "sourceDescription": "",
                "shopId": "5764607714484028278",
                "displayStatus": 4,
                "initiator": "",
                "responsible": "",
                "reason": "",
                "deliveryType": 1,
                "deliveryTypeText": "DiDi",
                "currency": "COP",
                "orderIncome": 1988300,
                "orderIncomeDisplay": "$19.883",
                "incomeReduce": 0,
                "incomeReduceDisplay": "",
                "createTime": 1771460032,
                "createTimeOffsetInfo": {
                    "timestamp": 1771460032,
                    "offset": -18000
                },
                "displayInfo": {
                    "tips": "",
                    "statusText": "Completado",
                    "countDown": false,
                    "tags": [],
                    "type": 0
                },
                "shopPaidStatus": 0,
                "receiverInfo": {
                    "name": "Jefferson"
                },
                "statusTag": [],
                "subtotal": 4240000,
                "subtotalDisplay": "$42.400",
                "payType": 1,
                "payTag": {
                    "payType": 1
                }
            },
            {
                "orderId": "5764659826034540697",
                "orderIndex": 278005,
                "displayNum": "#278005",
                "sourceDescription": "",
                "shopId": "5764607714484028278",
                "displayStatus": 4,
                "initiator": "",
                "responsible": "",
                "reason": "",
                "deliveryType": 1,
                "deliveryTypeText": "DiDi",
                "currency": "COP",
                "orderIncome": 2419900,
                "orderIncomeDisplay": "$24.199",
                "incomeReduce": 0,
                "incomeReduceDisplay": "",
                "createTime": 1771459682,
                "createTimeOffsetInfo": {
                    "timestamp": 1771459682,
                    "offset": -18000
                },
                "displayInfo": {
                    "tips": "",
                    "statusText": "Completado",
                    "countDown": false,
                    "tags": [],
                    "type": 2
                },
                "shopPaidStatus": 0,
                "receiverInfo": {
                    "name": "Nicolas"
                },
                "statusTag": [],
                "subtotal": 4760000,
                "subtotalDisplay": "$47.600",
                "payType": 1,
                "payTag": {
                    "payType": 1
                }
            },
            {
                "orderId": "5764659873929298029",
                "orderIndex": 278004,
                "displayNum": "#278004",
                "sourceDescription": "",
                "shopId": "5764607714484028278",
                "displayStatus": 4,
                "initiator": "",
                "responsible": "",
                "reason": "",
                "deliveryType": 1,
                "deliveryTypeText": "DiDi",
                "currency": "COP",
                "orderIncome": 1988300,
                "orderIncomeDisplay": "$19.883",
                "incomeReduce": 0,
                "incomeReduceDisplay": "",
                "createTime": 1771458806,
                "createTimeOffsetInfo": {
                    "timestamp": 1771458806,
                    "offset": -18000
                },
                "displayInfo": {
                    "tips": "",
                    "statusText": "Completado",
                    "countDown": false,
                    "tags": [],
                    "type": 0
                },
                "shopPaidStatus": 0,
                "receiverInfo": {
                    "name": "Julian"
                },
                "statusTag": [],
                "subtotal": 4240000,
                "subtotalDisplay": "$42.400",
                "payType": 1,
                "payTag": {
                    "payType": 1
                }
            },
            {
                "orderId": "5764660001343864856",
                "orderIndex": 278003,
                "displayNum": "#278003",
                "sourceDescription": "",
                "shopId": "5764607714484028278",
                "displayStatus": 4,
                "initiator": "",
                "responsible": "",
                "reason": "",
                "deliveryType": 1,
                "deliveryTypeText": "DiDi",
                "currency": "COP",
                "orderIncome": 1988300,
                "orderIncomeDisplay": "$19.883",
                "incomeReduce": 0,
                "incomeReduceDisplay": "",
                "createTime": 1771456139,
                "createTimeOffsetInfo": {
                    "timestamp": 1771456139,
                    "offset": -18000
                },
                "displayInfo": {
                    "tips": "",
                    "statusText": "Completado",
                    "countDown": false,
                    "tags": [],
                    "type": 0
                },
                "shopPaidStatus": 0,
                "receiverInfo": {
                    "name": "David"
                },
                "statusTag": [],
                "subtotal": 4240000,
                "subtotalDisplay": "$42.400",
                "payType": 1,
                "payTag": {
                    "payType": 1
                }
            },
            {
                "orderId": "5764659601211461592",
                "orderIndex": 278002,
                "displayNum": "#278002",
                "sourceDescription": "",
                "shopId": "5764607714484028278",
                "displayStatus": 4,
                "initiator": "",
                "responsible": "",
                "reason": "",
                "deliveryType": 1,
                "deliveryTypeText": "DiDi",
                "currency": "COP",
                "orderIncome": 2782500,
                "orderIncomeDisplay": "$27.825",
                "incomeReduce": 0,
                "incomeReduceDisplay": "",
                "createTime": 1771454399,
                "createTimeOffsetInfo": {
                    "timestamp": 1771454399,
                    "offset": -18000
                },
                "displayInfo": {
                    "tips": "",
                    "statusText": "Completado",
                    "countDown": false,
                    "tags": [],
                    "type": 0
                },
                "shopPaidStatus": 21,
                "receiverInfo": {
                    "name": "John"
                },
                "statusTag": [],
                "subtotal": 5050000,
                "subtotalDisplay": "$50.500",
                "payType": 1,
                "payTag": {
                    "payType": 1
                }
            }
        ],
        "totalPage": 2,
        "shopAppealGray": false,
        "gatedLaunch": {
            "version": "v2",
            "extend": {
                "info": ""
            }
        },
        "redirectInfo": {
            "version": "V3",
            "ext": {
                "info": ""
            }
        }
    }
}